__init__.py
celfa_callbacks.py
celfa_callbacks_plotter.py
celfa_data.py
celfa_ensemble.py
celfa_eval.py
celfa_exceptions.py
celfa_globals.py
celfa_train.py
playground.py
setup.py
celfa-0.0.2.dist-info/METADATA
celfa-0.0.2.dist-info/WHEEL
celfa-0.0.2.dist-info/licenses/LICENSE
celfa-0.0.2.dist-info/RECORD
