Metadata-Version: 2.1
Name: celfa
Version: 0.0.2
Summary: X
Project-URL: Homepage, https://github.com/s4294967296/cnn
Project-URL: Bug Tracker, https://github.com/s4294967296/cnn/issues
Author-email: Daniel Schmid <daniel.ds.schmid@gmail.com>
License-File: LICENSE
Classifier: License :: OSI Approved :: MIT License
Classifier: Operating System :: OS Independent
Classifier: Programming Language :: Python :: 3
Requires-Python: >=3.7
